LICENSE
MANIFEST.in
README
README.rst
setup.py
python_subitosms.egg-info/PKG-INFO
python_subitosms.egg-info/SOURCES.txt
python_subitosms.egg-info/dependency_links.txt
python_subitosms.egg-info/top_level.txt
subitosms/__init__.py
subitosms/backends.py
subitosms/core.py
subitosms/gateways.py
subitosms/test/__init__.py
subitosms/test/test_gateway.py